simple_steam_queries/__init__.py
simple_steam_queries/simple_steam_queries.py
simple_steam_queries-1.0.4.dist-info/LICENSE
simple_steam_queries-1.0.4.dist-info/METADATA
simple_steam_queries-1.0.4.dist-info/WHEEL
simple_steam_queries-1.0.4.dist-info/top_level.txt
simple_steam_queries-1.0.4.dist-info/RECORD
