Metadata-Version: 2.1
Name: simple-steam-queries
Version: 1.0.4
Summary: A python module that allows you to easily run Steam Master Server Query Protocol queries
Home-page: https://github.com/gspentzas1991/Simple-Steam-Queries
Author: Giannis Spentzas
Author-email: gspentzas1991@gmail.com
Classifier: Programming Language :: Python :: 3
Classifier: License :: OSI Approved :: MIT License
Classifier: Operating System :: OS Independent
License-File: LICENSE
Requires-Dist: steam
